humblebundle_downloader/__init__.py
humblebundle_downloader/cli.py
humblebundle_downloader/download_library.py
humblebundle_downloader-0.4.3.dist-info/LICENSE
humblebundle_downloader-0.4.3.dist-info/METADATA
humblebundle_downloader-0.4.3.dist-info/WHEEL
humblebundle_downloader-0.4.3.dist-info/entry_points.txt
humblebundle_downloader-0.4.3.dist-info/RECORD
