Metadata-Version: 2.1
Name: humblebundle-downloader
Version: 0.4.3
Summary: Download your Humble Bundle library
License: MIT
Author: Eddy Hintze
Author-email: eddy@gitx.codes
Requires-Python: >=3.10,<4.0
Classifier: License :: OSI Approved :: MIT License
Classifier: Programming Language :: Python :: 3
Classifier: Programming Language :: Python :: 3.10
Classifier: Programming Language :: Python :: 3.11
Classifier: Programming Language :: Python :: 3.12
Requires-Dist: parsel (>=1.9.1,<2.0.0)
Requires-Dist: requests (>=2.32.3,<3.0.0)
Project-URL: homepage, https://github.com/xtream1101/humblebundle-downloader
Project-URL: repository, https://github.com/xtream1101/humblebundle-downloader
